BafPipe/__init__.py
BafPipe/baf2sql.py
BafPipe/baf2sql2unidec.py
BafPipe/baf2sql_c.dll
BafPipe/meta_processing.py
BafPipe/ms_plotter_tools.py
bafpipe-0.3.4.dist-info/licenses/LICENSE
bafpipe-0.3.4.dist-info/METADATA
bafpipe-0.3.4.dist-info/WHEEL
bafpipe-0.3.4.dist-info/top_level.txt
bafpipe-0.3.4.dist-info/RECORD
