Metadata-Version: 2.4
Name: BafPipe
Version: 0.3.4
Summary: Automated deconvolution of Bruker mass spectra datasets using UniDec
Home-page: https://github.com/lawrencecollins/BafPipe
Author: Lawrence Collins
Author-email: chmlco@leeds.ac.uk
Classifier: Programming Language :: Python :: 3
Classifier: License :: OSI Approved :: MIT License
Classifier: Operating System :: OS Independent
Requires-Python: >=3.6
License-File: LICENSE
Requires-Dist: unidec
Requires-Dist: seaborn
Dynamic: author
Dynamic: author-email
Dynamic: classifier
Dynamic: description
Dynamic: description-content-type
Dynamic: home-page
Dynamic: license-file
Dynamic: requires-dist
Dynamic: requires-python
Dynamic: summary
